[
  {
    "name": "table en bois pliante",
    "slug": "table en bois pliante",
    "tagline": "✔ 60cm×40cm×110cm
✔️ ارتفاع قابل للتعديل: من 63 سم إلى 90 سم لتناسب جميع الاستخدامات وتوفر الراحة
✔️ سهولة الحركة: عجلات متينة تسهّل نقلها إلى أي مكان في المنزل .
.",
    "price": "4900DA",
    "ctaText": "تقديم طلب",
    "trustMarker": "توصيل سريع 58 ولاية",
    "images": [
      "photo-1.jpg",
      "photo-2.jpg",
      "photo-3.jpg"
    ],
    "tallyFormUrl": "https://tally.so/embed/NpObvG",
    "pageTitle": "MKW STORE — تقديم طلب",
    "pageDescription": "
✔️ ارتفاع قابل للتعديل: من 63 سم إلى 90 سم لتناسب جميع الاستخدامات وتوفر الراحة
✔️ سهولة الحركة: عجلات متينة تسهّل نقلها إلى أي مكان في المنزل .
."."
  },
  {
    "name": "Super Gadget",
    "slug": "super-gadget",
    "tagline": "One device. Endless possibilities.",
    "price": "$79",
    "ctaText": "Order Now",
    "trustMarker": "Free shipping • 60-day guarantee",
    "images": [
      "gadget-1.jpg",
      "gadget-2.jpg",
      "gadget-3.jpg",
      "gadget-4.jpg"
    ],
    "tallyFormUrl": "https://tally.so/embed/def456",
    "pageTitle": "Super Gadget — Order Now",
    "pageDescription": "One device. Endless possibilities. Super Gadget is your everyday companion."
  }
]
